PowerSchoolPy
